ctrfoobar2000
