Metadata-Version: 1.1
Name: ctrfoobar2000
Version: 1.2.0.2
Summary: Control Foobar2000 with python + Command line
Home-page: https://codecumulus13.wordpress.com
Author: Laode Hadi Cahyadi
Author-email: licface@yahoo.com
License: MIT
Download-URL: https://github.com/cumulus13/ctrfoobar2000/archive/v1.2(t0.2).tar.gz
Keywords: foobar2000,foobar,com,http,cli,command line
Platform: Platform Independent
Classifier: Environment :: Console
Classifier: Intended Audience :: Developers
Classifier: Intended Audience :: Information Technology
Classifier: Development Status :: 3 - Alpha
Classifier: License :: OSI Approved :: MIT License
Classifier: Programming Language :: Python :: 2.6
Classifier: Programming Language :: Python :: 2.7
Classifier: Topic :: Text Processing :: General
Classifier: Topic :: Software Development :: Libraries :: Python Modules
Classifier: Topic :: System :: Software Distribution
Classifier: Topic :: Utilities
Classifier: Operating System :: OS Independent
